ctg_analysis/__init__.py
ctg_analysis/ctg_analysis.py
ctg_analysis-0.0.1.dist-info/LICENSE.txt
ctg_analysis-0.0.1.dist-info/METADATA
ctg_analysis-0.0.1.dist-info/WHEEL
ctg_analysis-0.0.1.dist-info/top_level.txt
ctg_analysis-0.0.1.dist-info/RECORD
