Metadata-Version: 2.1
Name: ctg-analysis
Version: 0.0.1
Summary: Python library for the automatic cardiotocogram (CTG) analysis and interpretation
Home-page: https://github.com/mlinaresv/ctg_analysis
Author: Maxi Linares
Author-email: maxi-linares@hotmail.com
Classifier: Programming Language :: Python :: 3
Classifier: License :: Other/Proprietary License
Classifier: Operating System :: OS Independent
Requires-Python: >=3.7
License-File: LICENSE.txt
Requires-Dist: matplotlib (>=3.5.1)
Requires-Dist: BaselineRemoval (>=0.1.4)
Requires-Dist: numpy (>=1.16.0)
Requires-Dist: scipy (>=1.7.0)
Requires-Dist: pandas (>=1.2.0)
